Metadata-Version: 2.1
Name: chronoTrigger
Version: 0.1.1
Summary: Library for working with intervals
Author-email: dmitriybreus5@gmail.com
